scripts/__init__.py
scripts/cli.py
scripts/client.py
scripts/utils/__init__.py
scripts/utils/cli_helpers.py
scripts/utils/github_helpers.py
scripts/utils/models.py
scripts/utils/tc_helpers.py
scripts/utils/trigger_helpers.py
tests/__init__.py
tests/test_smth.py
cloudshell_tc_scripts-4.1.3.dist-info/METADATA
cloudshell_tc_scripts-4.1.3.dist-info/WHEEL
cloudshell_tc_scripts-4.1.3.dist-info/entry_points.txt
cloudshell_tc_scripts-4.1.3.dist-info/top_level.txt
cloudshell_tc_scripts-4.1.3.dist-info/RECORD
