Metadata-Version: 2.1
Name: cloudshell-tc-scripts
Version: 4.1.3
Summary: Cloudshell TC scripts
Home-page: http://www.qualisystems.com/
Author: QualiSystems
Author-email: info@qualisystems.com
Requires-Python: ~=3.9
Requires-Dist: pygithub (~=1.54)
Requires-Dist: click (~=8.0)
Requires-Dist: requests (~=2.25)
Requires-Dist: pydantic (~=1.7)
Requires-Dist: dohq-teamcity (~=1.0.5)
Requires-Dist: teamcity-messages (~=1.28)
